{
  "schema_version": 1,
  "generated_at": "1970-01-01T00:00:00Z",
  "generator": "scripts/render_composition_sketches.py",
  "source_files": [
    "compositions/down-tempo-punk-bluegrass-set.json",
    "compositions/composition-mutation-blueprints.json",
    "automation/live12-session-template.json"
  ],
  "source_file_sha256": {
    "compositions/down-tempo-punk-bluegrass-set.json": "d7ace3ba0abc6d17758caa587c052818002f76825a024dab5f5ced531bdff488",
    "compositions/composition-mutation-blueprints.json": "624dc1263c1932822d631e7d6cd5be0a39192265f87f0670b859f429dd6e9191",
    "automation/live12-session-template.json": "f17640bd3d24a4f6953836393c3286a45c7ba9c9064399590611dac566c76c51"
  },
  "purpose": "Deterministic MIDI and Live-build plans for standalone downtempo punk-bluegrass tracks.",
  "ableton_import_notes": [
    "Create or open a Live 12 session from automation/live12-session-template.json.",
    "Drag each .mid file into Live and route generated MIDI tracks to matching session tracks.",
    "Replace GM placeholder sounds with the documented Ableton/Arturia instruments only after license verification.",
    "Use composition_mutation_blueprint for per-track role jobs, mutation lanes, and section-level review targets.",
    "Use Max for Live device contracts in each plan as the automation target list."
  ],
  "tracks": [
    {
      "title": "Good Vibrations in a Burned Barn",
      "slug": "good-vibrations-in-a-burned-barn",
      "tempo_bpm": 96,
      "key_center": "D mixolydian",
      "duration_target": "4:20",
      "approximate_bars": 120,
      "midi_file": "compositions/generated/midi/good-vibrations-in-a-burned-barn.mid",
      "midi_sha256": "9dd16949691ef1477ffab2b66fb86ad01efb8384f69ca8a16d3d07550ee78cf0",
      "midi_byte_size": 54481,
      "scenes": [
        {
          "index": 1,
          "name": "01 field-texture intro with public-domain source deck muted until cleared",
          "bar_start": 1,
          "bar_length": 20,
          "arrangement_note": "field-texture intro with public-domain source deck muted until cleared"
        },
        {
          "index": 2,
          "name": "02 banjo roll establishes hook over kick-free pulse",
          "bar_start": 21,
          "bar_length": 20,
          "arrangement_note": "banjo roll establishes hook over kick-free pulse"
        },
        {
          "index": 3,
          "name": "03 deep-house kick enters under mandolin chop",
          "bar_start": 41,
          "bar_length": 20,
          "arrangement_note": "deep-house kick enters under mandolin chop"
        },
        {
          "index": 4,
          "name": "04 fiddle answer bends into granular sky",
          "bar_start": 61,
          "bar_length": 20,
          "arrangement_note": "fiddle answer bends into granular sky"
        },
        {
          "index": 5,
          "name": "05 half-time punk break",
          "bar_start": 81,
          "bar_length": 20,
          "arrangement_note": "half-time punk break"
        },
        {
          "index": 6,
          "name": "06 final chorus with source deck slices if provenance approved",
          "bar_start": 101,
          "bar_length": 20,
          "arrangement_note": "final chorus with source deck slices if provenance approved"
        }
      ],
      "layers": [
        {
          "id": "aeroband_banjo_lead",
          "session_track": "AeroBand Banjo Lead",
          "midi_track": "AeroBand Banjo Lead",
          "midi_channels": [
            1
          ],
          "gm_sound": "Banjo",
          "motif": "Sixteenth-note forward roll with section-density changes.",
          "traditional_bluegrass_layer": true,
          "alien_electronic_layer": false,
          "device_contracts": [
            "m4l.aeroband_banjo_mapper",
            "m4l.roll_probability_engine"
          ],
          "automation_targets": [
            "velocity_curve",
            "roll_density",
            "pluck_decay",
            "humanize_ms"
          ]
        },
        {
          "id": "fiddle_hybrid_strings",
          "session_track": "Fiddle / Hybrid Strings",
          "midi_track": "Fiddle / Hybrid Strings",
          "midi_channels": [
            2
          ],
          "gm_sound": "Violin",
          "motif": "Long root/fifth drones and answer tones for fiddle-family contour.",
          "traditional_bluegrass_layer": true,
          "alien_electronic_layer": true,
          "device_contracts": [
            "m4l.call_response_router"
          ],
          "automation_targets": [
            "bow_noise",
            "vibrato_depth",
            "send_spatial"
          ]
        },
        {
          "id": "mandolin_chop",
          "session_track": "Mandolin Chop",
          "midi_track": "Mandolin Chop",
          "midi_channels": [
            3
          ],
          "gm_sound": "Steel Guitar proxy",
          "motif": "Short offbeat chop chords on beats two and four.",
          "traditional_bluegrass_layer": true,
          "alien_electronic_layer": false,
          "device_contracts": [
            "m4l.chop_clock_guard"
          ],
          "automation_targets": [
            "chop_gate",
            "ghost_note_probability"
          ]
        },
        {
          "id": "dobro_metallic_slide",
          "session_track": "Dobro / Metallic Slide",
          "midi_track": "Dobro / Metallic Slide",
          "midi_channels": [
            4
          ],
          "gm_sound": "Jazz Guitar proxy",
          "motif": "Sparse slide-like approaches into section roots.",
          "traditional_bluegrass_layer": true,
          "alien_electronic_layer": true,
          "device_contracts": [
            "m4l.slide_phrase_sampler"
          ],
          "automation_targets": [
            "glide_time",
            "feedback",
            "spectral_tilt"
          ]
        },
        {
          "id": "upright_bass_sub",
          "session_track": "Upright Bass / Sub",
          "midi_track": "Upright Bass / Sub",
          "midi_channels": [
            5
          ],
          "gm_sound": "Acoustic Bass",
          "motif": "Root/fifth walk doubled conceptually by sidechained sub.",
          "traditional_bluegrass_layer": true,
          "alien_electronic_layer": true,
          "device_contracts": [
            "m4l.root_motion_limiter"
          ],
          "automation_targets": [
            "sub_blend",
            "sidechain_depth",
            "note_length"
          ]
        },
        {
          "id": "acoustic_guitar_boom_chuck",
          "session_track": "Acoustic Guitar Boom-Chuck",
          "midi_track": "Acoustic Guitar Boom-Chuck",
          "midi_channels": [
            6
          ],
          "gm_sound": "Steel Guitar",
          "motif": "Alternating bass-note boom and short chord chuck for bluegrass rhythm drive.",
          "traditional_bluegrass_layer": true,
          "alien_electronic_layer": false,
          "device_contracts": [
            "m4l.chop_clock_guard",
            "m4l.call_response_router"
          ],
          "automation_targets": [
            "boom_chuck_balance",
            "strum_velocity",
            "room_send",
            "downstroke_bias"
          ]
        },
        {
          "id": "punk_kit",
          "session_track": "Punk Kit",
          "midi_track": "Punk Kit",
          "midi_channels": [
            10
          ],
          "gm_sound": "GM Drum Kit",
          "motif": "Dry kick/snare/hat hits with end-of-section fills.",
          "traditional_bluegrass_layer": false,
          "alien_electronic_layer": false,
          "device_contracts": [
            "m4l.fill_trigger"
          ],
          "automation_targets": [
            "parallel_drive",
            "room_send",
            "fill_probability"
          ]
        },
        {
          "id": "deep_house_machines",
          "session_track": "Deep House Machines",
          "midi_track": "Deep House Machines",
          "midi_channels": [
            10,
            11
          ],
          "gm_sound": "GM drum machine plus synth-stab channel",
          "motif": "Four-on-floor kick, hats, claps, and minor chord stabs.",
          "traditional_bluegrass_layer": false,
          "alien_electronic_layer": true,
          "device_contracts": [
            "m4l.house_grid_conductor"
          ],
          "automation_targets": [
            "filter_cutoff",
            "accent",
            "swing_amount"
          ]
        },
        {
          "id": "alien_sky",
          "session_track": "Alien Sky",
          "midi_track": "Alien Sky",
          "midi_channels": [
            12
          ],
          "gm_sound": "Warm Pad",
          "motif": "Wide held tones for Granulator/PitchLoop/spectral processing.",
          "traditional_bluegrass_layer": false,
          "alien_electronic_layer": true,
          "device_contracts": [
            "m4l.spatial_harmonic_field"
          ],
          "automation_targets": [
            "azimuth",
            "width",
            "grain_density",
            "freeze"
          ]
        }
      ],
      "max_for_live_focus": [
        "roll_probability_engine",
        "spatial_harmonic_field"
      ],
      "bluegrass_core": [
        "AeroBand banjo lead",
        "fiddle drone",
        "mandolin chop",
        "upright bass"
      ],
      "electronic_dna": [
        "sidechained sub",
        "granular vocal-like pads",
        "909 hat pulse"
      ],
      "punk_spirit": [
        "two-chord chorus",
        "dry kit hits",
        "shouted gang-response placeholders"
      ],
      "composition_mutation_blueprint": {
        "slug": "good-vibrations-in-a-burned-barn",
        "title": "Good Vibrations in a Burned Barn",
        "hook_thesis": "A controller-banjo forward roll behaves like a modular pop hook while the room collapses into a barn-fire punk refrain.",
        "testable_appeal_hypothesis": "Hypothesis: repeated bright banjo cells, delayed fiddle answers, and a late four-on-floor entrance will improve recall without making the track feel polished.",
        "traditional_role_jobs": {
          "aeroband_banjo_lead": "Play the lead hook as Brian Wilson-style cell repetition, with velocity changes preserved from the controller.",
          "fiddle_hybrid_strings": "Answer the hook with long mixolydian drones and bowed lift into the chorus.",
          "mandolin_chop": "Provide offbeat lift on beats two and four, then thin out during the half-time break.",
          "dobro_metallic_slide": "Enter as a bent harmony shadow after the first house-kick arrival.",
          "acoustic_guitar_boom_chuck": "Hold the dry barn-floor rhythm bed under the banjo without masking the roll.",
          "upright_bass_sub": "Double root and fifth movement with low-end restraint and sidechain headroom."
        },
        "alien_role_jobs": {
          "deep_house_machines": "Delay the kick entrance so the house grid feels earned, then lock the mandolin chop to it.",
          "alien_sky": "Granularly smear fiddle answers into a wide freeze bloom after the fourth section.",
          "public_domain_source_deck": "Prefer old-time reel and hornpipe candidates for micro-slices only after provenance approval."
        },
        "punk_role_jobs": {
          "punk_kit": "Use dry snare hits and a half-time break rather than cinematic drum programming.",
          "performance_rule": "Keep one lead-controller take with audible risk before comping.",
          "anti_polish_rule": "Leave a controlled edge on pick noise, snare room, and final chorus crowd response."
        },
        "source_deck_plan": {
          "candidate_strategy": "Use generated source candidates for rhythmic DNA and do not expose raw local sample paths.",
          "deck_state": "muted_until_human_provenance_review",
          "approval_gate": "live_set_mutation",
          "credit_policy": "Carry Citizen DJ / Library of Congress credit into release notes if any source deck slice is unmuted."
        },
        "mutation_lanes": [
          {
            "device_id": "m4l.aeroband_banjo_mapper",
            "target_role_id": "aeroband_banjo_lead",
            "musical_purpose": "Map controller gestures into banjo-like pluck articulation.",
            "automation_shape": "velocity_curve rises from intimate verse to shouted chorus.",
            "approval_gate": "live_set_mutation"
          },
          {
            "device_id": "m4l.roll_probability_engine",
            "target_role_id": "aeroband_banjo_lead",
            "musical_purpose": "Keep the roll varied without erasing the hook.",
            "automation_shape": "roll_density increases at each chorus return.",
            "approval_gate": "live_set_mutation"
          },
          {
            "device_id": "m4l.spatial_harmonic_field",
            "target_role_id": "alien_sky",
            "musical_purpose": "Open the final chorus into an alien stereo field.",
            "automation_shape": "width and freeze rise only after the half-time break.",
            "approval_gate": "live_set_mutation"
          }
        ],
        "section_blueprints": [
          {
            "arrangement_index": 1,
            "section_function": "prove the texture before rhythm",
            "mutation_focus": "source deck stays muted while alien sky establishes dust",
            "energy_shape": "low static",
            "source_deck_state": "muted"
          },
          {
            "arrangement_index": 2,
            "section_function": "teach the banjo hook",
            "mutation_focus": "controller articulation and roll probability",
            "energy_shape": "human lift",
            "source_deck_state": "muted"
          },
          {
            "arrangement_index": 3,
            "section_function": "attach the dance grid",
            "mutation_focus": "house kick enters under mandolin chop",
            "energy_shape": "steady ramp",
            "source_deck_state": "muted"
          },
          {
            "arrangement_index": 4,
            "section_function": "make the fiddle answer uncanny",
            "mutation_focus": "spatial harmonic field and granular tails",
            "energy_shape": "wide bloom",
            "source_deck_state": "muted"
          },
          {
            "arrangement_index": 5,
            "section_function": "break the polish",
            "mutation_focus": "punk kit and half-time dry room",
            "energy_shape": "abrupt drop",
            "source_deck_state": "muted"
          },
          {
            "arrangement_index": 6,
            "section_function": "return with provenance-safe slices",
            "mutation_focus": "source deck slices only after review",
            "energy_shape": "high chorus",
            "source_deck_state": "candidate_slices_after_review"
          }
        ]
      },
      "production_constraints": [
        "Import MIDI into Ableton Live 12, then map each MIDI track to the matching session-template track.",
        "Keep Public Domain Source Deck muted until the source ledger approves the selected audio.",
        "Do not commit rendered audio, .als, .amxd, commercial packs, samples, presets, or controller recordings.",
        "Before Live-set mutation, save a local rollback copy and record the affected tracks/devices."
      ]
    },
    {
      "title": "A.P. Carter in the Warehouse",
      "slug": "a-p-carter-in-the-warehouse",
      "tempo_bpm": 88,
      "key_center": "A minor / dorian interchange",
      "duration_target": "3:45",
      "approximate_bars": 100,
      "midi_file": "compositions/generated/midi/a-p-carter-in-the-warehouse.mid",
      "midi_sha256": "eb5dffb6e310e7794b3a72ff8fd02799720029d9456e4091e63e3a42249e6920",
      "midi_byte_size": 45395,
      "scenes": [
        {
          "index": 1,
          "name": "01 dobro hook alone",
          "bar_start": 1,
          "bar_length": 20,
          "arrangement_note": "dobro hook alone"
        },
        {
          "index": 2,
          "name": "02 warehouse kick and sub enter",
          "bar_start": 21,
          "bar_length": 20,
          "arrangement_note": "warehouse kick and sub enter"
        },
        {
          "index": 3,
          "name": "03 call-and-response between banjo and stab",
          "bar_start": 41,
          "bar_length": 20,
          "arrangement_note": "call-and-response between banjo and stab"
        },
        {
          "index": 4,
          "name": "04 bridge strips to voice, stomp, and bowed harmonic",
          "bar_start": 61,
          "bar_length": 20,
          "arrangement_note": "bridge strips to voice, stomp, and bowed harmonic"
        },
        {
          "index": 5,
          "name": "05 return with doubled banjo/dobro riff",
          "bar_start": 81,
          "bar_length": 20,
          "arrangement_note": "return with doubled banjo/dobro riff"
        }
      ],
      "layers": [
        {
          "id": "aeroband_banjo_lead",
          "session_track": "AeroBand Banjo Lead",
          "midi_track": "AeroBand Banjo Lead",
          "midi_channels": [
            1
          ],
          "gm_sound": "Banjo",
          "motif": "Sixteenth-note forward roll with section-density changes.",
          "traditional_bluegrass_layer": true,
          "alien_electronic_layer": false,
          "device_contracts": [
            "m4l.aeroband_banjo_mapper",
            "m4l.roll_probability_engine"
          ],
          "automation_targets": [
            "velocity_curve",
            "roll_density",
            "pluck_decay",
            "humanize_ms"
          ]
        },
        {
          "id": "fiddle_hybrid_strings",
          "session_track": "Fiddle / Hybrid Strings",
          "midi_track": "Fiddle / Hybrid Strings",
          "midi_channels": [
            2
          ],
          "gm_sound": "Violin",
          "motif": "Long root/fifth drones and answer tones for fiddle-family contour.",
          "traditional_bluegrass_layer": true,
          "alien_electronic_layer": true,
          "device_contracts": [
            "m4l.call_response_router"
          ],
          "automation_targets": [
            "bow_noise",
            "vibrato_depth",
            "send_spatial"
          ]
        },
        {
          "id": "mandolin_chop",
          "session_track": "Mandolin Chop",
          "midi_track": "Mandolin Chop",
          "midi_channels": [
            3
          ],
          "gm_sound": "Steel Guitar proxy",
          "motif": "Short offbeat chop chords on beats two and four.",
          "traditional_bluegrass_layer": true,
          "alien_electronic_layer": false,
          "device_contracts": [
            "m4l.chop_clock_guard"
          ],
          "automation_targets": [
            "chop_gate",
            "ghost_note_probability"
          ]
        },
        {
          "id": "dobro_metallic_slide",
          "session_track": "Dobro / Metallic Slide",
          "midi_track": "Dobro / Metallic Slide",
          "midi_channels": [
            4
          ],
          "gm_sound": "Jazz Guitar proxy",
          "motif": "Sparse slide-like approaches into section roots.",
          "traditional_bluegrass_layer": true,
          "alien_electronic_layer": true,
          "device_contracts": [
            "m4l.slide_phrase_sampler"
          ],
          "automation_targets": [
            "glide_time",
            "feedback",
            "spectral_tilt"
          ]
        },
        {
          "id": "upright_bass_sub",
          "session_track": "Upright Bass / Sub",
          "midi_track": "Upright Bass / Sub",
          "midi_channels": [
            5
          ],
          "gm_sound": "Acoustic Bass",
          "motif": "Root/fifth walk doubled conceptually by sidechained sub.",
          "traditional_bluegrass_layer": true,
          "alien_electronic_layer": true,
          "device_contracts": [
            "m4l.root_motion_limiter"
          ],
          "automation_targets": [
            "sub_blend",
            "sidechain_depth",
            "note_length"
          ]
        },
        {
          "id": "acoustic_guitar_boom_chuck",
          "session_track": "Acoustic Guitar Boom-Chuck",
          "midi_track": "Acoustic Guitar Boom-Chuck",
          "midi_channels": [
            6
          ],
          "gm_sound": "Steel Guitar",
          "motif": "Alternating bass-note boom and short chord chuck for bluegrass rhythm drive.",
          "traditional_bluegrass_layer": true,
          "alien_electronic_layer": false,
          "device_contracts": [
            "m4l.chop_clock_guard",
            "m4l.call_response_router"
          ],
          "automation_targets": [
            "boom_chuck_balance",
            "strum_velocity",
            "room_send",
            "downstroke_bias"
          ]
        },
        {
          "id": "punk_kit",
          "session_track": "Punk Kit",
          "midi_track": "Punk Kit",
          "midi_channels": [
            10
          ],
          "gm_sound": "GM Drum Kit",
          "motif": "Dry kick/snare/hat hits with end-of-section fills.",
          "traditional_bluegrass_layer": false,
          "alien_electronic_layer": false,
          "device_contracts": [
            "m4l.fill_trigger"
          ],
          "automation_targets": [
            "parallel_drive",
            "room_send",
            "fill_probability"
          ]
        },
        {
          "id": "deep_house_machines",
          "session_track": "Deep House Machines",
          "midi_track": "Deep House Machines",
          "midi_channels": [
            10,
            11
          ],
          "gm_sound": "GM drum machine plus synth-stab channel",
          "motif": "Four-on-floor kick, hats, claps, and minor chord stabs.",
          "traditional_bluegrass_layer": false,
          "alien_electronic_layer": true,
          "device_contracts": [
            "m4l.house_grid_conductor"
          ],
          "automation_targets": [
            "filter_cutoff",
            "accent",
            "swing_amount"
          ]
        },
        {
          "id": "alien_sky",
          "session_track": "Alien Sky",
          "midi_track": "Alien Sky",
          "midi_channels": [
            12
          ],
          "gm_sound": "Warm Pad",
          "motif": "Wide held tones for Granulator/PitchLoop/spectral processing.",
          "traditional_bluegrass_layer": false,
          "alien_electronic_layer": true,
          "device_contracts": [
            "m4l.spatial_harmonic_field"
          ],
          "automation_targets": [
            "azimuth",
            "width",
            "grain_density",
            "freeze"
          ]
        }
      ],
      "max_for_live_focus": [
        "call_response_router",
        "house_grid_conductor"
      ],
      "bluegrass_core": [
        "banjo imitation",
        "dobro slide",
        "acoustic guitar boom-chuck",
        "fiddle tremolo"
      ],
      "electronic_dna": [
        "lowpassed deep-house chord stab",
        "dub send",
        "granular reverse tails"
      ],
      "punk_spirit": [
        "plainspoken topline",
        "minimal bridge",
        "distorted room crush"
      ],
      "composition_mutation_blueprint": {
        "slug": "a-p-carter-in-the-warehouse",
        "title": "A.P. Carter in the Warehouse",
        "hook_thesis": "A plainspoken dobro hook moves like a Carter Family melody inside a slow warehouse kick and dub-return system.",
        "testable_appeal_hypothesis": "Hypothesis: sparse narrative phrasing plus call-response stabs will feel intimate while the low-passed house pulse keeps bodies moving.",
        "traditional_role_jobs": {
          "aeroband_banjo_lead": "Answer the dobro hook with restrained banjo imitation rather than constant roll density.",
          "fiddle_hybrid_strings": "Provide tremolo tension behind the bridge and soften the final return.",
          "mandolin_chop": "Mark the warehouse backbeat with dry offbeat punctuation.",
          "dobro_metallic_slide": "Carry the lead thesis through bends, slides, and chorus pickups.",
          "acoustic_guitar_boom_chuck": "Keep boom-chuck phrasing plain and narrative, close to the vocal pocket.",
          "upright_bass_sub": "Bridge acoustic root movement into deep-house sub without busy passing tones."
        },
        "alien_role_jobs": {
          "deep_house_machines": "Use low-passed stabs as the answering voice to banjo and dobro.",
          "alien_sky": "Reserve reverse granular tails for the stripped bridge.",
          "public_domain_source_deck": "Prefer ballad-contour candidates only after provenance review."
        },
        "punk_role_jobs": {
          "punk_kit": "Crush the room in the bridge but avoid festival-rock polish.",
          "performance_rule": "Keep the topline phrasing plain, close, and under-edited.",
          "anti_polish_rule": "Let warehouse noise and imperfect slide attacks remain audible."
        },
        "source_deck_plan": {
          "candidate_strategy": "Use source candidates for contour reference, not as full-song substitution.",
          "deck_state": "muted_until_human_provenance_review",
          "approval_gate": "live_set_mutation",
          "credit_policy": "Credit Citizen DJ / Library of Congress if source deck audio is used."
        },
        "mutation_lanes": [
          {
            "device_id": "m4l.call_response_router",
            "target_role_id": "fiddle_hybrid_strings",
            "musical_purpose": "Route banjo, fiddle, and stab answers around the dobro thesis.",
            "automation_shape": "answer density drops in the bridge then doubles at the return.",
            "approval_gate": "live_set_mutation"
          },
          {
            "device_id": "m4l.house_grid_conductor",
            "target_role_id": "deep_house_machines",
            "musical_purpose": "Keep the warehouse pulse slow but locked.",
            "automation_shape": "swing and accent rise through the second half.",
            "approval_gate": "live_set_mutation"
          }
        ],
        "section_blueprints": [
          {
            "arrangement_index": 1,
            "section_function": "state the dobro thesis",
            "mutation_focus": "slide phrase contour",
            "energy_shape": "solo reveal",
            "source_deck_state": "muted"
          },
          {
            "arrangement_index": 2,
            "section_function": "open the warehouse pulse",
            "mutation_focus": "kick and sub discipline",
            "energy_shape": "low ramp",
            "source_deck_state": "muted"
          },
          {
            "arrangement_index": 3,
            "section_function": "build call-response identity",
            "mutation_focus": "banjo and stab routing",
            "energy_shape": "locked groove",
            "source_deck_state": "muted"
          },
          {
            "arrangement_index": 4,
            "section_function": "strip to story and stomp",
            "mutation_focus": "room crush and bowed harmonic",
            "energy_shape": "negative space",
            "source_deck_state": "muted"
          },
          {
            "arrangement_index": 5,
            "section_function": "return with doubled riff",
            "mutation_focus": "dobro and banjo unison risk",
            "energy_shape": "controlled lift",
            "source_deck_state": "candidate_slices_after_review"
          }
        ]
      },
      "production_constraints": [
        "Import MIDI into Ableton Live 12, then map each MIDI track to the matching session-template track.",
        "Keep Public Domain Source Deck muted until the source ledger approves the selected audio.",
        "Do not commit rendered audio, .als, .amxd, commercial packs, samples, presets, or controller recordings.",
        "Before Live-set mutation, save a local rollback copy and record the affected tracks/devices."
      ]
    },
    {
      "title": "No Gods, No Masters, No Quantize",
      "slug": "no-gods-no-masters-no-quantize",
      "tempo_bpm": 104,
      "key_center": "G major with flat-7 pressure",
      "duration_target": "3:10",
      "approximate_bars": 100,
      "midi_file": "compositions/generated/midi/no-gods-no-masters-no-quantize.mid",
      "midi_sha256": "cea40e19e0a6be6e47a97eacf4fcbef65a901694aad7d77d746e5f24de79d59b",
      "midi_byte_size": 45360,
      "scenes": [
        {
          "index": 1,
          "name": "01 count-off into unquantized banjo",
          "bar_start": 1,
          "bar_length": 20,
          "arrangement_note": "count-off into unquantized banjo"
        },
        {
          "index": 2,
          "name": "02 kick locks after four bars",
          "bar_start": 21,
          "bar_length": 20,
          "arrangement_note": "kick locks after four bars"
        },
        {
          "index": 3,
          "name": "03 acid line mirrors bass roots",
          "bar_start": 41,
          "bar_length": 20,
          "arrangement_note": "acid line mirrors bass roots"
        },
        {
          "index": 4,
          "name": "04 stop-time chorus",
          "bar_start": 61,
          "bar_length": 20,
          "arrangement_note": "stop-time chorus"
        },
        {
          "index": 5,
          "name": "05 fiddle and spectral freeze outro",
          "bar_start": 81,
          "bar_length": 20,
          "arrangement_note": "fiddle and spectral freeze outro"
        }
      ],
      "layers": [
        {
          "id": "aeroband_banjo_lead",
          "session_track": "AeroBand Banjo Lead",
          "midi_track": "AeroBand Banjo Lead",
          "midi_channels": [
            1
          ],
          "gm_sound": "Banjo",
          "motif": "Sixteenth-note forward roll with section-density changes.",
          "traditional_bluegrass_layer": true,
          "alien_electronic_layer": false,
          "device_contracts": [
            "m4l.aeroband_banjo_mapper",
            "m4l.roll_probability_engine"
          ],
          "automation_targets": [
            "velocity_curve",
            "roll_density",
            "pluck_decay",
            "humanize_ms"
          ]
        },
        {
          "id": "fiddle_hybrid_strings",
          "session_track": "Fiddle / Hybrid Strings",
          "midi_track": "Fiddle / Hybrid Strings",
          "midi_channels": [
            2
          ],
          "gm_sound": "Violin",
          "motif": "Long root/fifth drones and answer tones for fiddle-family contour.",
          "traditional_bluegrass_layer": true,
          "alien_electronic_layer": true,
          "device_contracts": [
            "m4l.call_response_router"
          ],
          "automation_targets": [
            "bow_noise",
            "vibrato_depth",
            "send_spatial"
          ]
        },
        {
          "id": "mandolin_chop",
          "session_track": "Mandolin Chop",
          "midi_track": "Mandolin Chop",
          "midi_channels": [
            3
          ],
          "gm_sound": "Steel Guitar proxy",
          "motif": "Short offbeat chop chords on beats two and four.",
          "traditional_bluegrass_layer": true,
          "alien_electronic_layer": false,
          "device_contracts": [
            "m4l.chop_clock_guard"
          ],
          "automation_targets": [
            "chop_gate",
            "ghost_note_probability"
          ]
        },
        {
          "id": "dobro_metallic_slide",
          "session_track": "Dobro / Metallic Slide",
          "midi_track": "Dobro / Metallic Slide",
          "midi_channels": [
            4
          ],
          "gm_sound": "Jazz Guitar proxy",
          "motif": "Sparse slide-like approaches into section roots.",
          "traditional_bluegrass_layer": true,
          "alien_electronic_layer": true,
          "device_contracts": [
            "m4l.slide_phrase_sampler"
          ],
          "automation_targets": [
            "glide_time",
            "feedback",
            "spectral_tilt"
          ]
        },
        {
          "id": "upright_bass_sub",
          "session_track": "Upright Bass / Sub",
          "midi_track": "Upright Bass / Sub",
          "midi_channels": [
            5
          ],
          "gm_sound": "Acoustic Bass",
          "motif": "Root/fifth walk doubled conceptually by sidechained sub.",
          "traditional_bluegrass_layer": true,
          "alien_electronic_layer": true,
          "device_contracts": [
            "m4l.root_motion_limiter"
          ],
          "automation_targets": [
            "sub_blend",
            "sidechain_depth",
            "note_length"
          ]
        },
        {
          "id": "acoustic_guitar_boom_chuck",
          "session_track": "Acoustic Guitar Boom-Chuck",
          "midi_track": "Acoustic Guitar Boom-Chuck",
          "midi_channels": [
            6
          ],
          "gm_sound": "Steel Guitar",
          "motif": "Alternating bass-note boom and short chord chuck for bluegrass rhythm drive.",
          "traditional_bluegrass_layer": true,
          "alien_electronic_layer": false,
          "device_contracts": [
            "m4l.chop_clock_guard",
            "m4l.call_response_router"
          ],
          "automation_targets": [
            "boom_chuck_balance",
            "strum_velocity",
            "room_send",
            "downstroke_bias"
          ]
        },
        {
          "id": "punk_kit",
          "session_track": "Punk Kit",
          "midi_track": "Punk Kit",
          "midi_channels": [
            10
          ],
          "gm_sound": "GM Drum Kit",
          "motif": "Dry kick/snare/hat hits with end-of-section fills.",
          "traditional_bluegrass_layer": false,
          "alien_electronic_layer": false,
          "device_contracts": [
            "m4l.fill_trigger"
          ],
          "automation_targets": [
            "parallel_drive",
            "room_send",
            "fill_probability"
          ]
        },
        {
          "id": "deep_house_machines",
          "session_track": "Deep House Machines",
          "midi_track": "Deep House Machines",
          "midi_channels": [
            10,
            11
          ],
          "gm_sound": "GM drum machine plus synth-stab channel",
          "motif": "Four-on-floor kick, hats, claps, and minor chord stabs.",
          "traditional_bluegrass_layer": false,
          "alien_electronic_layer": true,
          "device_contracts": [
            "m4l.house_grid_conductor"
          ],
          "automation_targets": [
            "filter_cutoff",
            "accent",
            "swing_amount"
          ]
        },
        {
          "id": "alien_sky",
          "session_track": "Alien Sky",
          "midi_track": "Alien Sky",
          "midi_channels": [
            12
          ],
          "gm_sound": "Warm Pad",
          "motif": "Wide held tones for Granulator/PitchLoop/spectral processing.",
          "traditional_bluegrass_layer": false,
          "alien_electronic_layer": true,
          "device_contracts": [
            "m4l.spatial_harmonic_field"
          ],
          "automation_targets": [
            "azimuth",
            "width",
            "grain_density",
            "freeze"
          ]
        }
      ],
      "max_for_live_focus": [
        "chop_clock_guard",
        "root_motion_limiter"
      ],
      "bluegrass_core": [
        "fast banjo roll",
        "mandolin offbeats",
        "upright bass walk",
        "fiddle double-stop"
      ],
      "electronic_dna": [
        "acid bass shadow",
        "bitcrushed percussion",
        "spectral freeze fills"
      ],
      "punk_spirit": [
        "raw kit",
        "abrupt stops",
        "anti-polish vocal cadence"
      ],
      "composition_mutation_blueprint": {
        "slug": "no-gods-no-masters-no-quantize",
        "title": "No Gods, No Masters, No Quantize",
        "hook_thesis": "Fast banjo, abrupt punk stops, and a shadow acid line argue with the grid instead of obeying it.",
        "testable_appeal_hypothesis": "Hypothesis: slight timing friction between human roll and locked kick will create attention without collapsing danceability.",
        "traditional_role_jobs": {
          "aeroband_banjo_lead": "Lead with fast roll language and preserve unquantized attack variance.",
          "fiddle_hybrid_strings": "Use double-stops as stop-time exclamation points.",
          "mandolin_chop": "Cut through with clipped offbeats and ghost-note pressure.",
          "dobro_metallic_slide": "Add short metallic answers after abrupt stops.",
          "acoustic_guitar_boom_chuck": "Reinforce the anti-polish pulse with aggressive downstrokes.",
          "upright_bass_sub": "Mirror roots while the acid shadow threatens chromatic motion."
        },
        "alien_role_jobs": {
          "deep_house_machines": "Lock kick and acid-shadow stabs after the banjo establishes human drift.",
          "alien_sky": "Use spectral freeze only as a stop-time punctuation device.",
          "public_domain_source_deck": "Prefer reel and hornpipe candidates for transient chop studies after approval."
        },
        "punk_role_jobs": {
          "punk_kit": "Favor raw kit stops and short fills over smooth transitions.",
          "performance_rule": "Do not quantize the opening banjo count-off.",
          "anti_polish_rule": "Keep abrupt gaps and rough cadence as structural features."
        },
        "source_deck_plan": {
          "candidate_strategy": "Use source candidates as transient vocabulary after ledger and credit checks.",
          "deck_state": "muted_until_human_provenance_review",
          "approval_gate": "live_set_mutation",
          "credit_policy": "Credit Citizen DJ / Library of Congress in any released source-use notes."
        },
        "mutation_lanes": [
          {
            "device_id": "m4l.chop_clock_guard",
            "target_role_id": "mandolin_chop",
            "musical_purpose": "Prevent chop drift from hiding the intentionally unquantized banjo.",
            "automation_shape": "tighten only when kick and mandolin need to lock.",
            "approval_gate": "live_set_mutation"
          },
          {
            "device_id": "m4l.root_motion_limiter",
            "target_role_id": "upright_bass_sub",
            "musical_purpose": "Limit low-end chaos while the acid shadow pushes flat-seven pressure.",
            "automation_shape": "root constraint stays strong during stop-time choruses.",
            "approval_gate": "live_set_mutation"
          }
        ],
        "section_blueprints": [
          {
            "arrangement_index": 1,
            "section_function": "declare human timing",
            "mutation_focus": "unquantized banjo count-off",
            "energy_shape": "nervous start",
            "source_deck_state": "muted"
          },
          {
            "arrangement_index": 2,
            "section_function": "prove the grid can join",
            "mutation_focus": "kick enters after four bars",
            "energy_shape": "snap to floor",
            "source_deck_state": "muted"
          },
          {
            "arrangement_index": 3,
            "section_function": "introduce acid contradiction",
            "mutation_focus": "root limiter and bass mirror",
            "energy_shape": "pressurized",
            "source_deck_state": "muted"
          },
          {
            "arrangement_index": 4,
            "section_function": "weaponize silence",
            "mutation_focus": "stop-time chorus and kit cuts",
            "energy_shape": "hard cut",
            "source_deck_state": "muted"
          },
          {
            "arrangement_index": 5,
            "section_function": "freeze the argument",
            "mutation_focus": "fiddle and spectral freeze outro",
            "energy_shape": "ragged dissolve",
            "source_deck_state": "candidate_slices_after_review"
          }
        ]
      },
      "production_constraints": [
        "Import MIDI into Ableton Live 12, then map each MIDI track to the matching session-template track.",
        "Keep Public Domain Source Deck muted until the source ledger approves the selected audio.",
        "Do not commit rendered audio, .als, .amxd, commercial packs, samples, presets, or controller recordings.",
        "Before Live-set mutation, save a local rollback copy and record the affected tracks/devices."
      ]
    },
    {
      "title": "Possum Kingdom Afterhours",
      "slug": "possum-kingdom-afterhours",
      "tempo_bpm": 82,
      "key_center": "E minor pentatonic",
      "duration_target": "5:30",
      "approximate_bars": 120,
      "midi_file": "compositions/generated/midi/possum-kingdom-afterhours.mid",
      "midi_sha256": "070a6a4f7432eb8ea68aac2d1f62c763ed0c6b059540c390894b3b9dff47aa95",
      "midi_byte_size": 54358,
      "scenes": [
        {
          "index": 1,
          "name": "01 drone and fiddle establish place",
          "bar_start": 1,
          "bar_length": 24,
          "arrangement_note": "drone and fiddle establish place"
        },
        {
          "index": 2,
          "name": "02 brush kit and dub chords pulse",
          "bar_start": 25,
          "bar_length": 24,
          "arrangement_note": "brush kit and dub chords pulse"
        },
        {
          "index": 3,
          "name": "03 banjo harmonics become granular particles",
          "bar_start": 49,
          "bar_length": 24,
          "arrangement_note": "banjo harmonics become granular particles"
        },
        {
          "index": 4,
          "name": "04 dobro swell chorus",
          "bar_start": 73,
          "bar_length": 24,
          "arrangement_note": "dobro swell chorus"
        },
        {
          "index": 5,
          "name": "05 long spatial fade with low-end discipline",
          "bar_start": 97,
          "bar_length": 24,
          "arrangement_note": "long spatial fade with low-end discipline"
        }
      ],
      "layers": [
        {
          "id": "aeroband_banjo_lead",
          "session_track": "AeroBand Banjo Lead",
          "midi_track": "AeroBand Banjo Lead",
          "midi_channels": [
            1
          ],
          "gm_sound": "Banjo",
          "motif": "Sixteenth-note forward roll with section-density changes.",
          "traditional_bluegrass_layer": true,
          "alien_electronic_layer": false,
          "device_contracts": [
            "m4l.aeroband_banjo_mapper",
            "m4l.roll_probability_engine"
          ],
          "automation_targets": [
            "velocity_curve",
            "roll_density",
            "pluck_decay",
            "humanize_ms"
          ]
        },
        {
          "id": "fiddle_hybrid_strings",
          "session_track": "Fiddle / Hybrid Strings",
          "midi_track": "Fiddle / Hybrid Strings",
          "midi_channels": [
            2
          ],
          "gm_sound": "Violin",
          "motif": "Long root/fifth drones and answer tones for fiddle-family contour.",
          "traditional_bluegrass_layer": true,
          "alien_electronic_layer": true,
          "device_contracts": [
            "m4l.call_response_router"
          ],
          "automation_targets": [
            "bow_noise",
            "vibrato_depth",
            "send_spatial"
          ]
        },
        {
          "id": "mandolin_chop",
          "session_track": "Mandolin Chop",
          "midi_track": "Mandolin Chop",
          "midi_channels": [
            3
          ],
          "gm_sound": "Steel Guitar proxy",
          "motif": "Short offbeat chop chords on beats two and four.",
          "traditional_bluegrass_layer": true,
          "alien_electronic_layer": false,
          "device_contracts": [
            "m4l.chop_clock_guard"
          ],
          "automation_targets": [
            "chop_gate",
            "ghost_note_probability"
          ]
        },
        {
          "id": "dobro_metallic_slide",
          "session_track": "Dobro / Metallic Slide",
          "midi_track": "Dobro / Metallic Slide",
          "midi_channels": [
            4
          ],
          "gm_sound": "Jazz Guitar proxy",
          "motif": "Sparse slide-like approaches into section roots.",
          "traditional_bluegrass_layer": true,
          "alien_electronic_layer": true,
          "device_contracts": [
            "m4l.slide_phrase_sampler"
          ],
          "automation_targets": [
            "glide_time",
            "feedback",
            "spectral_tilt"
          ]
        },
        {
          "id": "upright_bass_sub",
          "session_track": "Upright Bass / Sub",
          "midi_track": "Upright Bass / Sub",
          "midi_channels": [
            5
          ],
          "gm_sound": "Acoustic Bass",
          "motif": "Root/fifth walk doubled conceptually by sidechained sub.",
          "traditional_bluegrass_layer": true,
          "alien_electronic_layer": true,
          "device_contracts": [
            "m4l.root_motion_limiter"
          ],
          "automation_targets": [
            "sub_blend",
            "sidechain_depth",
            "note_length"
          ]
        },
        {
          "id": "acoustic_guitar_boom_chuck",
          "session_track": "Acoustic Guitar Boom-Chuck",
          "midi_track": "Acoustic Guitar Boom-Chuck",
          "midi_channels": [
            6
          ],
          "gm_sound": "Steel Guitar",
          "motif": "Alternating bass-note boom and short chord chuck for bluegrass rhythm drive.",
          "traditional_bluegrass_layer": true,
          "alien_electronic_layer": false,
          "device_contracts": [
            "m4l.chop_clock_guard",
            "m4l.call_response_router"
          ],
          "automation_targets": [
            "boom_chuck_balance",
            "strum_velocity",
            "room_send",
            "downstroke_bias"
          ]
        },
        {
          "id": "punk_kit",
          "session_track": "Punk Kit",
          "midi_track": "Punk Kit",
          "midi_channels": [
            10
          ],
          "gm_sound": "GM Drum Kit",
          "motif": "Dry kick/snare/hat hits with end-of-section fills.",
          "traditional_bluegrass_layer": false,
          "alien_electronic_layer": false,
          "device_contracts": [
            "m4l.fill_trigger"
          ],
          "automation_targets": [
            "parallel_drive",
            "room_send",
            "fill_probability"
          ]
        },
        {
          "id": "deep_house_machines",
          "session_track": "Deep House Machines",
          "midi_track": "Deep House Machines",
          "midi_channels": [
            10,
            11
          ],
          "gm_sound": "GM drum machine plus synth-stab channel",
          "motif": "Four-on-floor kick, hats, claps, and minor chord stabs.",
          "traditional_bluegrass_layer": false,
          "alien_electronic_layer": true,
          "device_contracts": [
            "m4l.house_grid_conductor"
          ],
          "automation_targets": [
            "filter_cutoff",
            "accent",
            "swing_amount"
          ]
        },
        {
          "id": "alien_sky",
          "session_track": "Alien Sky",
          "midi_track": "Alien Sky",
          "midi_channels": [
            12
          ],
          "gm_sound": "Warm Pad",
          "motif": "Wide held tones for Granulator/PitchLoop/spectral processing.",
          "traditional_bluegrass_layer": false,
          "alien_electronic_layer": true,
          "device_contracts": [
            "m4l.spatial_harmonic_field"
          ],
          "automation_targets": [
            "azimuth",
            "width",
            "grain_density",
            "freeze"
          ]
        }
      ],
      "max_for_live_focus": [
        "spatial_harmonic_field",
        "provenance_sampler"
      ],
      "bluegrass_core": [
        "modal fiddle",
        "banjo harmonics",
        "dobro swells",
        "brush kit"
      ],
      "electronic_dna": [
        "slow dub-techno chords",
        "sub drone",
        "Inspired by Nature modulation"
      ],
      "punk_spirit": [
        "one-take lead rule",
        "feedback edges",
        "no glossy breakdown"
      ],
      "composition_mutation_blueprint": {
        "slug": "possum-kingdom-afterhours",
        "title": "Possum Kingdom Afterhours",
        "hook_thesis": "A slow modal fiddle place-study becomes dub-techno bluegrass afterhours without losing one-take lead risk.",
        "testable_appeal_hypothesis": "Hypothesis: low tempo, modal repetition, and long spatial fade will create sustained immersion while feedback edges keep the track from becoming ambient wallpaper.",
        "traditional_role_jobs": {
          "aeroband_banjo_lead": "Use harmonics and sparse roll fragments rather than lead runs.",
          "fiddle_hybrid_strings": "Own the modal identity with bowed place-setting drones.",
          "mandolin_chop": "Enter rarely as a dry pulse marker against dub chords.",
          "dobro_metallic_slide": "Swell into chorus spaces and answer the fiddle without stealing focus.",
          "acoustic_guitar_boom_chuck": "Keep a low, brushed rhythm bed under the dub-techno chord movement.",
          "upright_bass_sub": "Hold root gravity and sub drone with strict mono discipline."
        },
        "alien_role_jobs": {
          "deep_house_machines": "Use slow dub-techno chords, restrained hats, and deep sidechain rather than peak-time programming.",
          "alien_sky": "Turn banjo harmonics into granular particles and long spatial fade.",
          "public_domain_source_deck": "Prefer hornpipe contour candidates for distant counter-lines after approval."
        },
        "punk_role_jobs": {
          "punk_kit": "Use brush kit and feedback edges instead of glossy breakdowns.",
          "performance_rule": "Keep a one-take lead rule for the primary controller pass.",
          "anti_polish_rule": "No cinematic riser before the chorus; let the swell stay handmade."
        },
        "source_deck_plan": {
          "candidate_strategy": "Use source candidates as quiet contour ghosts only after provenance review.",
          "deck_state": "muted_until_human_provenance_review",
          "approval_gate": "live_set_mutation",
          "credit_policy": "Carry Citizen DJ / Library of Congress credit if any approved source appears."
        },
        "mutation_lanes": [
          {
            "device_id": "m4l.spatial_harmonic_field",
            "target_role_id": "alien_sky",
            "musical_purpose": "Move drones and harmonics through a spatial field without masking low end.",
            "automation_shape": "azimuth and width drift slowly across the full arrangement.",
            "approval_gate": "live_set_mutation"
          },
          {
            "device_id": "m4l.provenance_sampler",
            "target_role_id": "public_domain_source_deck",
            "musical_purpose": "Gate any historical fragments behind ledger-backed approval.",
            "automation_shape": "slice_index remains inactive until human review unmute.",
            "approval_gate": "live_set_mutation"
          }
        ],
        "section_blueprints": [
          {
            "arrangement_index": 1,
            "section_function": "establish place",
            "mutation_focus": "fiddle drone and sub restraint",
            "energy_shape": "low hover",
            "source_deck_state": "muted"
          },
          {
            "arrangement_index": 2,
            "section_function": "start afterhours pulse",
            "mutation_focus": "brush kit and dub chords",
            "energy_shape": "slow pulse",
            "source_deck_state": "muted"
          },
          {
            "arrangement_index": 3,
            "section_function": "make banjo harmonic alien",
            "mutation_focus": "granular particle lane",
            "energy_shape": "textural lift",
            "source_deck_state": "muted"
          },
          {
            "arrangement_index": 4,
            "section_function": "swell the chorus by hand",
            "mutation_focus": "dobro feedback and room send",
            "energy_shape": "wide swell",
            "source_deck_state": "muted"
          },
          {
            "arrangement_index": 5,
            "section_function": "fade with discipline",
            "mutation_focus": "spatial field and low-end mono check",
            "energy_shape": "long fade",
            "source_deck_state": "candidate_slices_after_review"
          }
        ]
      },
      "production_constraints": [
        "Import MIDI into Ableton Live 12, then map each MIDI track to the matching session-template track.",
        "Keep Public Domain Source Deck muted until the source ledger approves the selected audio.",
        "Do not commit rendered audio, .als, .amxd, commercial packs, samples, presets, or controller recordings.",
        "Before Live-set mutation, save a local rollback copy and record the affected tracks/devices."
      ]
    },
    {
      "title": "The Ballad of the Broken Controller",
      "slug": "the-ballad-of-the-broken-controller",
      "tempo_bpm": 100,
      "key_center": "B flat major with punk chromatic passing tones",
      "duration_target": "4:00",
      "approximate_bars": 100,
      "midi_file": "compositions/generated/midi/the-ballad-of-the-broken-controller.mid",
      "midi_sha256": "0806d648fef1d4388b926ded3f4958573b1fbd61c5c2a016c69e3bf991d299fd",
      "midi_byte_size": 45431,
      "scenes": [
        {
          "index": 1,
          "name": "01 controller calibration noises become rhythm",
          "bar_start": 1,
          "bar_length": 20,
          "arrangement_note": "controller calibration noises become rhythm"
        },
        {
          "index": 2,
          "name": "02 banjo riff locks to glitch percussion",
          "bar_start": 21,
          "bar_length": 20,
          "arrangement_note": "banjo riff locks to glitch percussion"
        },
        {
          "index": 3,
          "name": "03 mandolin tremolo lifts refrain",
          "bar_start": 41,
          "bar_length": 20,
          "arrangement_note": "mandolin tremolo lifts refrain"
        },
        {
          "index": 4,
          "name": "04 breakdown exposes failed notes",
          "bar_start": 61,
          "bar_length": 20,
          "arrangement_note": "breakdown exposes failed notes"
        },
        {
          "index": 5,
          "name": "05 final refrain stacks all traditional instruments over alien choir",
          "bar_start": 81,
          "bar_length": 20,
          "arrangement_note": "final refrain stacks all traditional instruments over alien choir"
        }
      ],
      "layers": [
        {
          "id": "aeroband_banjo_lead",
          "session_track": "AeroBand Banjo Lead",
          "midi_track": "AeroBand Banjo Lead",
          "midi_channels": [
            1
          ],
          "gm_sound": "Banjo",
          "motif": "Sixteenth-note forward roll with section-density changes.",
          "traditional_bluegrass_layer": true,
          "alien_electronic_layer": false,
          "device_contracts": [
            "m4l.aeroband_banjo_mapper",
            "m4l.roll_probability_engine"
          ],
          "automation_targets": [
            "velocity_curve",
            "roll_density",
            "pluck_decay",
            "humanize_ms"
          ]
        },
        {
          "id": "fiddle_hybrid_strings",
          "session_track": "Fiddle / Hybrid Strings",
          "midi_track": "Fiddle / Hybrid Strings",
          "midi_channels": [
            2
          ],
          "gm_sound": "Violin",
          "motif": "Long root/fifth drones and answer tones for fiddle-family contour.",
          "traditional_bluegrass_layer": true,
          "alien_electronic_layer": true,
          "device_contracts": [
            "m4l.call_response_router"
          ],
          "automation_targets": [
            "bow_noise",
            "vibrato_depth",
            "send_spatial"
          ]
        },
        {
          "id": "mandolin_chop",
          "session_track": "Mandolin Chop",
          "midi_track": "Mandolin Chop",
          "midi_channels": [
            3
          ],
          "gm_sound": "Steel Guitar proxy",
          "motif": "Short offbeat chop chords on beats two and four.",
          "traditional_bluegrass_layer": true,
          "alien_electronic_layer": false,
          "device_contracts": [
            "m4l.chop_clock_guard"
          ],
          "automation_targets": [
            "chop_gate",
            "ghost_note_probability"
          ]
        },
        {
          "id": "dobro_metallic_slide",
          "session_track": "Dobro / Metallic Slide",
          "midi_track": "Dobro / Metallic Slide",
          "midi_channels": [
            4
          ],
          "gm_sound": "Jazz Guitar proxy",
          "motif": "Sparse slide-like approaches into section roots.",
          "traditional_bluegrass_layer": true,
          "alien_electronic_layer": true,
          "device_contracts": [
            "m4l.slide_phrase_sampler"
          ],
          "automation_targets": [
            "glide_time",
            "feedback",
            "spectral_tilt"
          ]
        },
        {
          "id": "upright_bass_sub",
          "session_track": "Upright Bass / Sub",
          "midi_track": "Upright Bass / Sub",
          "midi_channels": [
            5
          ],
          "gm_sound": "Acoustic Bass",
          "motif": "Root/fifth walk doubled conceptually by sidechained sub.",
          "traditional_bluegrass_layer": true,
          "alien_electronic_layer": true,
          "device_contracts": [
            "m4l.root_motion_limiter"
          ],
          "automation_targets": [
            "sub_blend",
            "sidechain_depth",
            "note_length"
          ]
        },
        {
          "id": "acoustic_guitar_boom_chuck",
          "session_track": "Acoustic Guitar Boom-Chuck",
          "midi_track": "Acoustic Guitar Boom-Chuck",
          "midi_channels": [
            6
          ],
          "gm_sound": "Steel Guitar",
          "motif": "Alternating bass-note boom and short chord chuck for bluegrass rhythm drive.",
          "traditional_bluegrass_layer": true,
          "alien_electronic_layer": false,
          "device_contracts": [
            "m4l.chop_clock_guard",
            "m4l.call_response_router"
          ],
          "automation_targets": [
            "boom_chuck_balance",
            "strum_velocity",
            "room_send",
            "downstroke_bias"
          ]
        },
        {
          "id": "punk_kit",
          "session_track": "Punk Kit",
          "midi_track": "Punk Kit",
          "midi_channels": [
            10
          ],
          "gm_sound": "GM Drum Kit",
          "motif": "Dry kick/snare/hat hits with end-of-section fills.",
          "traditional_bluegrass_layer": false,
          "alien_electronic_layer": false,
          "device_contracts": [
            "m4l.fill_trigger"
          ],
          "automation_targets": [
            "parallel_drive",
            "room_send",
            "fill_probability"
          ]
        },
        {
          "id": "deep_house_machines",
          "session_track": "Deep House Machines",
          "midi_track": "Deep House Machines",
          "midi_channels": [
            10,
            11
          ],
          "gm_sound": "GM drum machine plus synth-stab channel",
          "motif": "Four-on-floor kick, hats, claps, and minor chord stabs.",
          "traditional_bluegrass_layer": false,
          "alien_electronic_layer": true,
          "device_contracts": [
            "m4l.house_grid_conductor"
          ],
          "automation_targets": [
            "filter_cutoff",
            "accent",
            "swing_amount"
          ]
        },
        {
          "id": "alien_sky",
          "session_track": "Alien Sky",
          "midi_track": "Alien Sky",
          "midi_channels": [
            12
          ],
          "gm_sound": "Warm Pad",
          "motif": "Wide held tones for Granulator/PitchLoop/spectral processing.",
          "traditional_bluegrass_layer": false,
          "alien_electronic_layer": true,
          "device_contracts": [
            "m4l.spatial_harmonic_field"
          ],
          "automation_targets": [
            "azimuth",
            "width",
            "grain_density",
            "freeze"
          ]
        }
      ],
      "max_for_live_focus": [
        "aeroband_banjo_mapper",
        "fill_trigger"
      ],
      "bluegrass_core": [
        "AeroBand banjo lead",
        "mandolin tremolo",
        "upright slap",
        "fiddle saw"
      ],
      "electronic_dna": [
        "glitch percussion",
        "resampled controller errors",
        "wide synthetic choir"
      ],
      "punk_spirit": [
        "failure-as-hook",
        "short loud refrain",
        "live controller risk retained"
      ],
      "composition_mutation_blueprint": {
        "slug": "the-ballad-of-the-broken-controller",
        "title": "The Ballad of the Broken Controller",
        "hook_thesis": "Controller failure becomes the hook when bluegrass instruments, glitch percussion, and a synthetic choir refuse to hide the mistake.",
        "testable_appeal_hypothesis": "Hypothesis: audible failure framed as rhythm will increase memorability while the full acoustic stack keeps the song grounded.",
        "traditional_role_jobs": {
          "aeroband_banjo_lead": "Let calibration noise and controller slips shape the lead riff.",
          "fiddle_hybrid_strings": "Saw into the refrain with raw support rather than clean string pads.",
          "mandolin_chop": "Use tremolo lift to make the refrain feel communal.",
          "dobro_metallic_slide": "Bend around failed notes and make recovery audible.",
          "acoustic_guitar_boom_chuck": "Anchor the refrain with short, loud strums.",
          "upright_bass_sub": "Use slap-like attacks against the glitch rhythm without overloading the sub."
        },
        "alien_role_jobs": {
          "deep_house_machines": "Convert controller errors into glitch percussion while preserving the banjo riff.",
          "alien_sky": "Stack a wide synthetic choir behind the last refrain.",
          "public_domain_source_deck": "Use approved source candidates only as texture behind the failure motif."
        },
        "punk_role_jobs": {
          "punk_kit": "Make the refrain short, loud, and physically clipped.",
          "performance_rule": "Retain at least one failed controller event as a documented hook element.",
          "anti_polish_rule": "Do not smooth every pitch bend or MIDI mistrigger."
        },
        "source_deck_plan": {
          "candidate_strategy": "Keep public-domain fragments secondary to the controller-failure hook.",
          "deck_state": "muted_until_human_provenance_review",
          "approval_gate": "live_set_mutation",
          "credit_policy": "Credit Citizen DJ / Library of Congress if any source deck layer is active."
        },
        "mutation_lanes": [
          {
            "device_id": "m4l.aeroband_banjo_mapper",
            "target_role_id": "aeroband_banjo_lead",
            "musical_purpose": "Translate controller instability into playable banjo articulation.",
            "automation_shape": "humanize_ms increases during failure-reveal sections.",
            "approval_gate": "live_set_mutation"
          },
          {
            "device_id": "m4l.fill_trigger",
            "target_role_id": "punk_kit",
            "musical_purpose": "Answer controller mistakes with bounded punk fills.",
            "automation_shape": "fill_probability spikes at breakdown and final refrain.",
            "approval_gate": "live_set_mutation"
          }
        ],
        "section_blueprints": [
          {
            "arrangement_index": 1,
            "section_function": "turn calibration into rhythm",
            "mutation_focus": "controller noise capture as MIDI intent",
            "energy_shape": "quirky start",
            "source_deck_state": "muted"
          },
          {
            "arrangement_index": 2,
            "section_function": "lock riff to glitch",
            "mutation_focus": "banjo mapper and glitch percussion",
            "energy_shape": "tight loop",
            "source_deck_state": "muted"
          },
          {
            "arrangement_index": 3,
            "section_function": "lift refrain communally",
            "mutation_focus": "mandolin tremolo and gang cadence",
            "energy_shape": "upward push",
            "source_deck_state": "muted"
          },
          {
            "arrangement_index": 4,
            "section_function": "expose failure",
            "mutation_focus": "failed notes remain audible",
            "energy_shape": "raw reveal",
            "source_deck_state": "muted"
          },
          {
            "arrangement_index": 5,
            "section_function": "stack the whole machine",
            "mutation_focus": "full traditional stack over alien choir",
            "energy_shape": "maximal refrain",
            "source_deck_state": "candidate_slices_after_review"
          }
        ]
      },
      "production_constraints": [
        "Import MIDI into Ableton Live 12, then map each MIDI track to the matching session-template track.",
        "Keep Public Domain Source Deck muted until the source ledger approves the selected audio.",
        "Do not commit rendered audio, .als, .amxd, commercial packs, samples, presets, or controller recordings.",
        "Before Live-set mutation, save a local rollback copy and record the affected tracks/devices."
      ]
    },
    {
      "title": "Rail Yard Ghost in the Control Room",
      "slug": "rail-yard-ghost-in-the-control-room",
      "tempo_bpm": 94,
      "key_center": "C dorian",
      "duration_target": "4:48",
      "approximate_bars": 128,
      "midi_file": "compositions/generated/midi/rail-yard-ghost-in-the-control-room.mid",
      "midi_sha256": "6591072ba470b3775da4cfdbadb15d1042d469c7e466a17527051592be30293f",
      "midi_byte_size": 58246,
      "scenes": [
        {
          "index": 1,
          "name": "01 operator preflight drone with source deck muted",
          "bar_start": 1,
          "bar_length": 16,
          "arrangement_note": "operator preflight drone with source deck muted"
        },
        {
          "index": 2,
          "name": "02 AeroBand banjo calibration becomes forward-roll hook",
          "bar_start": 17,
          "bar_length": 16,
          "arrangement_note": "AeroBand banjo calibration becomes forward-roll hook"
        },
        {
          "index": 3,
          "name": "03 house grid conductor locks kick, hats, and mandolin chop",
          "bar_start": 33,
          "bar_length": 16,
          "arrangement_note": "house grid conductor locks kick, hats, and mandolin chop"
        },
        {
          "index": 4,
          "name": "04 call-response fiddle, guitar, and dobro orbit the hook",
          "bar_start": 49,
          "bar_length": 16,
          "arrangement_note": "call-response fiddle, guitar, and dobro orbit the hook"
        },
        {
          "index": 5,
          "name": "05 root motion limiter drops bass and sub under punk kit pushes",
          "bar_start": 65,
          "bar_length": 16,
          "arrangement_note": "root motion limiter drops bass and sub under punk kit pushes"
        },
        {
          "index": 6,
          "name": "06 provenance sampler gate opens only on approved source stutters",
          "bar_start": 81,
          "bar_length": 16,
          "arrangement_note": "provenance sampler gate opens only on approved source stutters"
        },
        {
          "index": 7,
          "name": "07 alien sky freeze and spatial harmonic field bloom",
          "bar_start": 97,
          "bar_length": 16,
          "arrangement_note": "alien sky freeze and spatial harmonic field bloom"
        },
        {
          "index": 8,
          "name": "08 one-take punk outro with bounded fills and rollback-safe stop",
          "bar_start": 113,
          "bar_length": 16,
          "arrangement_note": "one-take punk outro with bounded fills and rollback-safe stop"
        }
      ],
      "layers": [
        {
          "id": "aeroband_banjo_lead",
          "session_track": "AeroBand Banjo Lead",
          "midi_track": "AeroBand Banjo Lead",
          "midi_channels": [
            1
          ],
          "gm_sound": "Banjo",
          "motif": "Sixteenth-note forward roll with section-density changes.",
          "traditional_bluegrass_layer": true,
          "alien_electronic_layer": false,
          "device_contracts": [
            "m4l.aeroband_banjo_mapper",
            "m4l.roll_probability_engine"
          ],
          "automation_targets": [
            "velocity_curve",
            "roll_density",
            "pluck_decay",
            "humanize_ms"
          ]
        },
        {
          "id": "fiddle_hybrid_strings",
          "session_track": "Fiddle / Hybrid Strings",
          "midi_track": "Fiddle / Hybrid Strings",
          "midi_channels": [
            2
          ],
          "gm_sound": "Violin",
          "motif": "Long root/fifth drones and answer tones for fiddle-family contour.",
          "traditional_bluegrass_layer": true,
          "alien_electronic_layer": true,
          "device_contracts": [
            "m4l.call_response_router"
          ],
          "automation_targets": [
            "bow_noise",
            "vibrato_depth",
            "send_spatial"
          ]
        },
        {
          "id": "mandolin_chop",
          "session_track": "Mandolin Chop",
          "midi_track": "Mandolin Chop",
          "midi_channels": [
            3
          ],
          "gm_sound": "Steel Guitar proxy",
          "motif": "Short offbeat chop chords on beats two and four.",
          "traditional_bluegrass_layer": true,
          "alien_electronic_layer": false,
          "device_contracts": [
            "m4l.chop_clock_guard"
          ],
          "automation_targets": [
            "chop_gate",
            "ghost_note_probability"
          ]
        },
        {
          "id": "dobro_metallic_slide",
          "session_track": "Dobro / Metallic Slide",
          "midi_track": "Dobro / Metallic Slide",
          "midi_channels": [
            4
          ],
          "gm_sound": "Jazz Guitar proxy",
          "motif": "Sparse slide-like approaches into section roots.",
          "traditional_bluegrass_layer": true,
          "alien_electronic_layer": true,
          "device_contracts": [
            "m4l.slide_phrase_sampler"
          ],
          "automation_targets": [
            "glide_time",
            "feedback",
            "spectral_tilt"
          ]
        },
        {
          "id": "upright_bass_sub",
          "session_track": "Upright Bass / Sub",
          "midi_track": "Upright Bass / Sub",
          "midi_channels": [
            5
          ],
          "gm_sound": "Acoustic Bass",
          "motif": "Root/fifth walk doubled conceptually by sidechained sub.",
          "traditional_bluegrass_layer": true,
          "alien_electronic_layer": true,
          "device_contracts": [
            "m4l.root_motion_limiter"
          ],
          "automation_targets": [
            "sub_blend",
            "sidechain_depth",
            "note_length"
          ]
        },
        {
          "id": "acoustic_guitar_boom_chuck",
          "session_track": "Acoustic Guitar Boom-Chuck",
          "midi_track": "Acoustic Guitar Boom-Chuck",
          "midi_channels": [
            6
          ],
          "gm_sound": "Steel Guitar",
          "motif": "Alternating bass-note boom and short chord chuck for bluegrass rhythm drive.",
          "traditional_bluegrass_layer": true,
          "alien_electronic_layer": false,
          "device_contracts": [
            "m4l.chop_clock_guard",
            "m4l.call_response_router"
          ],
          "automation_targets": [
            "boom_chuck_balance",
            "strum_velocity",
            "room_send",
            "downstroke_bias"
          ]
        },
        {
          "id": "punk_kit",
          "session_track": "Punk Kit",
          "midi_track": "Punk Kit",
          "midi_channels": [
            10
          ],
          "gm_sound": "GM Drum Kit",
          "motif": "Dry kick/snare/hat hits with end-of-section fills.",
          "traditional_bluegrass_layer": false,
          "alien_electronic_layer": false,
          "device_contracts": [
            "m4l.fill_trigger"
          ],
          "automation_targets": [
            "parallel_drive",
            "room_send",
            "fill_probability"
          ]
        },
        {
          "id": "deep_house_machines",
          "session_track": "Deep House Machines",
          "midi_track": "Deep House Machines",
          "midi_channels": [
            10,
            11
          ],
          "gm_sound": "GM drum machine plus synth-stab channel",
          "motif": "Four-on-floor kick, hats, claps, and minor chord stabs.",
          "traditional_bluegrass_layer": false,
          "alien_electronic_layer": true,
          "device_contracts": [
            "m4l.house_grid_conductor"
          ],
          "automation_targets": [
            "filter_cutoff",
            "accent",
            "swing_amount"
          ]
        },
        {
          "id": "alien_sky",
          "session_track": "Alien Sky",
          "midi_track": "Alien Sky",
          "midi_channels": [
            12
          ],
          "gm_sound": "Warm Pad",
          "motif": "Wide held tones for Granulator/PitchLoop/spectral processing.",
          "traditional_bluegrass_layer": false,
          "alien_electronic_layer": true,
          "device_contracts": [
            "m4l.spatial_harmonic_field"
          ],
          "automation_targets": [
            "azimuth",
            "width",
            "grain_density",
            "freeze"
          ]
        }
      ],
      "max_for_live_focus": [
        "aeroband_banjo_mapper",
        "roll_probability_engine",
        "call_response_router",
        "chop_clock_guard",
        "slide_phrase_sampler",
        "root_motion_limiter",
        "fill_trigger",
        "house_grid_conductor",
        "provenance_sampler",
        "spatial_harmonic_field"
      ],
      "bluegrass_core": [
        "AeroBand banjo lead",
        "fiddle answer",
        "mandolin chop",
        "dobro swells",
        "upright bass"
      ],
      "electronic_dna": [
        "four-on-floor house grid",
        "sidechained sub",
        "glitch source-deck stutters",
        "spatial freeze bloom"
      ],
      "punk_spirit": [
        "one-take controller risk",
        "short loud refrain",
        "bounded drum fills",
        "no glossy outro"
      ],
      "composition_mutation_blueprint": {
        "slug": "rail-yard-ghost-in-the-control-room",
        "title": "Rail Yard Ghost in the Control Room",
        "hook_thesis": "The full system test: AeroBand banjo, every bluegrass support voice, public-domain stutters, and all Max for Live devices move through a controlled rail-yard ghost story.",
        "testable_appeal_hypothesis": "Hypothesis: complete-stack orchestration with bounded device mutation will create the strongest tactile performance identity while preserving provenance safety.",
        "traditional_role_jobs": {
          "aeroband_banjo_lead": "Lead the whole arrangement with controller-banjo calibration, forward-roll hook, and one-take risk.",
          "fiddle_hybrid_strings": "Answer the hook in orbiting phrases and widen into spectral bloom.",
          "mandolin_chop": "Lock the chop to house hats while keeping the bluegrass pulse readable.",
          "dobro_metallic_slide": "Swell around the hook as a haunted steel counter-line.",
          "acoustic_guitar_boom_chuck": "Bind the rail-yard rhythm bed with dry strums and call-response support.",
          "upright_bass_sub": "Keep bass and sub under strict root-motion and headroom limits."
        },
        "alien_role_jobs": {
          "deep_house_machines": "Run the four-on-floor grid, hats, and stabs as the control-room clock.",
          "alien_sky": "Bloom the final sections with spatial freeze and spectral harmonic motion.",
          "public_domain_source_deck": "Use approved source stutters as historical ghosts only after ledger-backed review."
        },
        "punk_role_jobs": {
          "punk_kit": "Use bounded fills and a short loud refrain without smoothing the outro.",
          "performance_rule": "Keep the lead controller risk audible across the final pass.",
          "anti_polish_rule": "No glossy outro; stop with a rollback-safe one-take edge."
        },
        "source_deck_plan": {
          "candidate_strategy": "Use generated candidates as stutters and call-response ghosts only after source IDs are verified in the ledger.",
          "deck_state": "muted_until_human_provenance_review",
          "approval_gate": "live_set_mutation",
          "credit_policy": "Carry Citizen DJ / Library of Congress credit lines into any release notes."
        },
        "mutation_lanes": [
          {
            "device_id": "m4l.aeroband_banjo_mapper",
            "target_role_id": "aeroband_banjo_lead",
            "musical_purpose": "Translate AeroBand controller data into banjo articulation.",
            "automation_shape": "velocity_curve and humanize_ms follow the performer risk arc.",
            "approval_gate": "live_set_mutation"
          },
          {
            "device_id": "m4l.roll_probability_engine",
            "target_role_id": "aeroband_banjo_lead",
            "musical_purpose": "Vary forward-roll density without losing the hook.",
            "automation_shape": "roll_density rises through each return.",
            "approval_gate": "live_set_mutation"
          },
          {
            "device_id": "m4l.call_response_router",
            "target_role_id": "fiddle_hybrid_strings",
            "musical_purpose": "Route fiddle, guitar, and dobro answers around the banjo hook.",
            "automation_shape": "answer density follows scene energy.",
            "approval_gate": "live_set_mutation"
          },
          {
            "device_id": "m4l.chop_clock_guard",
            "target_role_id": "mandolin_chop",
            "musical_purpose": "Keep chop timing locked to the house grid.",
            "automation_shape": "chop_gate tightens at grid entrances.",
            "approval_gate": "live_set_mutation"
          },
          {
            "device_id": "m4l.slide_phrase_sampler",
            "target_role_id": "dobro_metallic_slide",
            "musical_purpose": "Shape metallic slide phrases into haunted counter-lines.",
            "automation_shape": "glide_time and feedback rise in chorus swells.",
            "approval_gate": "live_set_mutation"
          },
          {
            "device_id": "m4l.root_motion_limiter",
            "target_role_id": "upright_bass_sub",
            "musical_purpose": "Protect low-end mono and root movement.",
            "automation_shape": "sidechain_depth stays strongest under kick-heavy scenes.",
            "approval_gate": "live_set_mutation"
          },
          {
            "device_id": "m4l.fill_trigger",
            "target_role_id": "punk_kit",
            "musical_purpose": "Generate bounded fills without derailing the arrangement.",
            "automation_shape": "fill_probability spikes before short loud refrains.",
            "approval_gate": "live_set_mutation"
          },
          {
            "device_id": "m4l.house_grid_conductor",
            "target_role_id": "deep_house_machines",
            "musical_purpose": "Conduct kick, hats, stabs, and swing as the control-room clock.",
            "automation_shape": "swing_amount and accent rise once the hook is established.",
            "approval_gate": "live_set_mutation"
          },
          {
            "device_id": "m4l.provenance_sampler",
            "target_role_id": "public_domain_source_deck",
            "musical_purpose": "Keep public-domain stutters gated by provenance checks.",
            "automation_shape": "slice_index remains inactive until review, then uses short stutters.",
            "approval_gate": "live_set_mutation"
          },
          {
            "device_id": "m4l.spatial_harmonic_field",
            "target_role_id": "alien_sky",
            "musical_purpose": "Bloom the final rail-yard ghost field.",
            "automation_shape": "width, azimuth, grain_density, and freeze expand through the outro.",
            "approval_gate": "live_set_mutation"
          }
        ],
        "section_blueprints": [
          {
            "arrangement_index": 1,
            "section_function": "run operator preflight as music",
            "mutation_focus": "source deck muted, drone active",
            "energy_shape": "procedural hush",
            "source_deck_state": "muted"
          },
          {
            "arrangement_index": 2,
            "section_function": "calibrate banjo hook",
            "mutation_focus": "AeroBand mapper and roll engine",
            "energy_shape": "human machine start",
            "source_deck_state": "muted"
          },
          {
            "arrangement_index": 3,
            "section_function": "lock the house clock",
            "mutation_focus": "house grid conductor and chop clock",
            "energy_shape": "floor lock",
            "source_deck_state": "muted"
          },
          {
            "arrangement_index": 4,
            "section_function": "orbit the hook",
            "mutation_focus": "call-response router across fiddle, guitar, dobro",
            "energy_shape": "braided lift",
            "source_deck_state": "muted"
          },
          {
            "arrangement_index": 5,
            "section_function": "protect low-end impact",
            "mutation_focus": "root limiter, punk kit, and sub headroom",
            "energy_shape": "heavy push",
            "source_deck_state": "muted"
          },
          {
            "arrangement_index": 6,
            "section_function": "open provenance gate",
            "mutation_focus": "provenance sampler only after approval",
            "energy_shape": "historical flicker",
            "source_deck_state": "candidate_slices_after_review"
          },
          {
            "arrangement_index": 7,
            "section_function": "bloom alien sky",
            "mutation_focus": "spatial harmonic field and freeze",
            "energy_shape": "wide spectral bloom",
            "source_deck_state": "candidate_slices_after_review"
          },
          {
            "arrangement_index": 8,
            "section_function": "end with one-take risk",
            "mutation_focus": "bounded fills and rollback-safe stop",
            "energy_shape": "ragged stop",
            "source_deck_state": "candidate_slices_after_review"
          }
        ]
      },
      "production_constraints": [
        "Import MIDI into Ableton Live 12, then map each MIDI track to the matching session-template track.",
        "Keep Public Domain Source Deck muted until the source ledger approves the selected audio.",
        "Do not commit rendered audio, .als, .amxd, commercial packs, samples, presets, or controller recordings.",
        "Before Live-set mutation, save a local rollback copy and record the affected tracks/devices."
      ]
    }
  ]
}
